cli_dependency_graph/__init__.py
cli_dependency_graph/__main__.py
cli_dependency_graph/analyzer.py
cli_dependency_graph/cli.py
cli_dependency_graph/renderer.py
cli_dependency_graph-0.1.0.dist-info/METADATA
cli_dependency_graph-0.1.0.dist-info/WHEEL
cli_dependency_graph-0.1.0.dist-info/entry_points.txt
cli_dependency_graph-0.1.0.dist-info/licenses/LICENSE
cli_dependency_graph-0.1.0.dist-info/RECORD
