Metadata-Version: 2.4
Name: cli-dependency-graph
Version: 0.1.0
Summary: CLI tool to statically analyze and visualize Click/Typer command trees.
Project-URL: Homepage, https://github.com/Najabi99/cli-dependency-graph
Author-email: Tamas Kovacs <kovacs.tamas03@gmail.com>
License-Expression: MIT
License-File: LICENSE
Classifier: Operating System :: OS Independent
Classifier: Programming Language :: Python :: 3
Requires-Python: >=3.9
Requires-Dist: click>=8.1.7
Requires-Dist: graphviz>=0.20.3
Requires-Dist: rich>=13.7.1
Requires-Dist: typer>=0.12.3
Provides-Extra: test
Requires-Dist: coverage; extra == 'test'
Requires-Dist: pytest; extra == 'test'
Requires-Dist: pytest-cov; extra == 'test'
